LICENSE
MANIFEST.in
README.md
setup.py
examples/__init__.py
examples/sync_native_token_owners.py
examples/sync_native_token_transfers.py
examples/sync_nft_sales.py
examples/restore_progress/__init__.py
examples/restore_progress/restore_sync_nft_sales.py
tests/core/__init__.py
tests/core/test_connection.py
tests/core/sync/__init__.py
tests/core/sync/test_sync_classification.py
tests/core/sync/test_sync_fetch_indexers.py
tests/core/sync/test_sync_indexer.py
tests/core/sync/test_sync_owner.py
tests/core/sync/test_sync_save_load_metadata.py
tests/core/sync/test_sync_transfer.py
transpose_dit/__init__.py
transpose_dit/__main__.py
transpose_dit.egg-info/PKG-INFO
transpose_dit.egg-info/SOURCES.txt
transpose_dit.egg-info/dependency_links.txt
transpose_dit.egg-info/requires.txt
transpose_dit.egg-info/top_level.txt
transpose_dit/common/__init__.py
transpose_dit/common/constants.py
transpose_dit/common/exceptions.py
transpose_dit/core/__init__.py
transpose_dit/core/main.py
transpose_dit/core/sync/__init__.py
transpose_dit/core/sync/main.py
transpose_dit/util/__init__.py
transpose_dit/util/io.py
transpose_dit/util/log.py
transpose_dit/util/testing.py
transpose_dit/util/threading.py
transpose_dit/util/time.py