Metadata-Version: 2.1
Name: transpose-dit
Version: 0.1.1
Summary: Web3 Data Made Simple. Powerful APIs for accessing human-readable blockchain data at scale: from blocks and transactions to NFTs and tokens.
Home-page: https://github.com/TransposeData/dedicated-instance-tools
Author: Jonathan Becker (jon-becker)
Author-email: jon@transpose.io
License: MIT
Keywords: web3,data,ethereum,web3 data,ethereum data
Classifier: Development Status :: 3 - Alpha
Classifier: Intended Audience :: Developers
Classifier: Intended Audience :: Information Technology
Classifier: License :: OSI Approved :: MIT License
Classifier: Natural Language :: English
Classifier: Topic :: Database
Classifier: Topic :: Utilities
License-File: LICENSE
